django_forms_encoder/__init__.py
django_forms_encoder/encoder.py
django_forms_encoder/tests/__init__.py
django_forms_encoder/tests/settings.py
django_forms_encoder/tests/test_encoder.py
django_forms_encoder-0.2.dist-info/LICENSE
django_forms_encoder-0.2.dist-info/METADATA
django_forms_encoder-0.2.dist-info/WHEEL
django_forms_encoder-0.2.dist-info/top_level.txt
django_forms_encoder-0.2.dist-info/RECORD
