Metadata-Version: 2.1
Name: django-forms-encoder
Version: 0.2
Summary: Encode django forms to JSON
Home-page: UNKNOWN
Author: Jan Musílek
Author-email: jan.musilek@nic.cz
License: UNKNOWN
Platform: UNKNOWN
Classifier: Development Status :: 2 - Pre-Alpha
Classifier: Environment :: Web Environment
Classifier: Intended Audience :: Developers
Classifier: License :: OSI Approved :: GNU General Public License v3 or later (GPLv3+)
Classifier: Operating System :: OS Independent
Classifier: Programming Language :: Python
Classifier: Programming Language :: Python :: 3.6
Classifier: Programming Language :: Python :: 3.7
Classifier: Programming Language :: Python :: 3.8
Requires-Python: >=3.6
Requires-Dist: Django (>=2.2)
Provides-Extra: quality
Requires-Dist: isort ; extra == 'quality'
Requires-Dist: flake8 ; extra == 'quality'
Requires-Dist: pydocstyle ; extra == 'quality'
Requires-Dist: mypy ; extra == 'quality'
